binaural_generator/__init__.py
binaural_generator/cli.py
binaural_generator/webapp.py
binaural_generator/core/__init__.py
binaural_generator/core/constants.py
binaural_generator/core/data_types.py
binaural_generator/core/exceptions.py
binaural_generator/core/fade.py
binaural_generator/core/noise.py
binaural_generator/core/parallel.py
binaural_generator/core/tone_generator.py
binaural_generator/core/utils.py
binaural_generator/scripts/creativity_blue.yaml
binaural_generator/scripts/creativity_theta.yaml
binaural_generator/scripts/focus_beta.yaml
binaural_generator/scripts/focus_gamma.yaml
binaural_generator/scripts/focus_violet.yaml
binaural_generator/scripts/lucid_dream_pink_noise.yaml
binaural_generator/scripts/lucid_dreaming.yaml
binaural_generator/scripts/meditation_theta.yaml
binaural_generator/scripts/migraine_relief.yaml
binaural_generator/scripts/relaxation_alpha.yaml
binaural_generator/scripts/relaxation_grey.yaml
binaural_generator/scripts/relaxation_ocean.yaml
binaural_generator/scripts/relaxation_rain.yaml
binaural_generator/scripts/sleep_delta.yaml
binaural_generator/webui/__init__.py
binaural_generator/webui/constants.py
binaural_generator/webui/main.py
binaural_generator/webui/components/__init__.py
binaural_generator/webui/components/audio_handlers.py
binaural_generator/webui/components/config_utils.py
binaural_generator/webui/components/sidebar.py
binaural_generator/webui/components/step_editor.py
binaural_generator/webui/components/ui_utils.py
binaural_generator-0.6.4.dist-info/licenses/LICENSE
tests/test_common.py
tests/test_data_types.py
tests/test_fade.py
tests/test_new_noise_types.py
tests/test_noise.py
tests/test_ocean_noise.py
tests/test_parallel.py
tests/test_property_based.py
tests/test_rain_noise.py
tests/test_tone_generator.py
tests/test_utils.py
binaural_generator-0.6.4.dist-info/METADATA
binaural_generator-0.6.4.dist-info/WHEEL
binaural_generator-0.6.4.dist-info/entry_points.txt
binaural_generator-0.6.4.dist-info/top_level.txt
binaural_generator-0.6.4.dist-info/RECORD
