Metadata-Version: 2.4
Name: binaural-generator
Version: 0.6.4
Summary: Generate binaural beat audio with background noise for brainwave entrainment
Author-email: Kayvan Sylvan <kayvan@sylvan.com>
License-Expression: MIT
Project-URL: Homepage, https://github.com/ksylvan/binaural-generator
Project-URL: Repository, https://github.com/ksylvan/binaural-generator
Project-URL: Bug Tracker, https://github.com/ksylvan/binaural-generator/issues
Project-URL: Documentation, https://github.com/ksylvan/binaural-generator#readme
Keywords: audio,binaural,beats,meditation,sound
Classifier: Development Status :: 3 - Alpha
Classifier: Intended Audience :: Developers
Classifier: Natural Language :: English
Classifier: Programming Language :: Python :: 3.10
Classifier: Programming Language :: Python :: 3.11
Classifier: Programming Language :: Python :: 3.12
Requires-Python: >=3.10
License-File: LICENSE
Requires-Dist: numpy>=2.2.4
Requires-Dist: pyyaml>=6.0.2
Requires-Dist: scipy>=1.15.2
Requires-Dist: soundfile>=0.13.1
Requires-Dist: streamlit>=1.44.1
Requires-Dist: watchdog>=6.0.0
Dynamic: license-file
